pg_purepy/__init__.py
pg_purepy/connection.py
pg_purepy/conversion/__init__.py
pg_purepy/conversion/_parse_hstore.py
pg_purepy/conversion/abc.py
pg_purepy/conversion/array_parse.py
pg_purepy/conversion/arrays.py
pg_purepy/conversion/basics.py
pg_purepy/conversion/dt.py
pg_purepy/conversion/enums.py
pg_purepy/conversion/hstore.py
pg_purepy/dbapi.py
pg_purepy/exc.py
pg_purepy/messages.py
pg_purepy/pool.py
pg_purepy/protocol.py
pg_purepy/py.typed
pg_purepy/util.py
pg_purepy-0.11.1.dist-info/LICENCE
pg_purepy-0.11.1.dist-info/LICENCE.GPL
pg_purepy-0.11.1.dist-info/METADATA
pg_purepy-0.11.1.dist-info/WHEEL
pg_purepy-0.11.1.dist-info/RECORD
